v5/__init__.py
v5/_version.py
v5/user_dict.txt
v5/v5.py
v5_relevance-1.1.4.dist-info/licenses/LICENSE
v5_relevance-1.1.4.dist-info/METADATA
v5_relevance-1.1.4.dist-info/WHEEL
v5_relevance-1.1.4.dist-info/top_level.txt
v5_relevance-1.1.4.dist-info/RECORD
