Metadata-Version: 2.4
Name: v5-relevance
Version: 1.1.4
Summary: V5版相关度算法 - 基于jieba的中文文本相关度计算
Home-page: https://github.com/your-username/v5-relevance
Author: 元龙居士
Author-email: 元龙居士 <your-email@example.com>
License: MIT
Project-URL: Homepage, https://github.com/your-username/v5-relevance
Project-URL: Documentation, https://github.com/your-username/v5-relevance#readme
Project-URL: Repository, https://github.com/your-username/v5-relevance
Project-URL: Issues, https://github.com/your-username/v5-relevance/issues
Keywords: relevance,chinese,text-analysis,jieba,nlp
Classifier: Development Status :: 4 - Beta
Classifier: Intended Audience :: Developers
Classifier: License :: OSI Approved :: MIT License
Classifier: Operating System :: OS Independent
Classifier: Programming Language :: Python :: 3
Classifier: Programming Language :: Python :: 3.7
Classifier: Programming Language :: Python :: 3.8
Classifier: Programming Language :: Python :: 3.9
Classifier: Programming Language :: Python :: 3.10
Classifier: Programming Language :: Python :: 3.11
Classifier: Topic :: Text Processing :: Linguistic
Classifier: Topic :: Software Development :: Libraries :: Python Modules
Requires-Python: >=3.7
License-File: LICENSE
Requires-Dist: jieba>=0.42.1
Provides-Extra: full
Requires-Dist: jieba>=0.42.1; extra == "full"
Provides-Extra: dev
Requires-Dist: pytest>=6.0; extra == "dev"
Requires-Dist: black>=21.0; extra == "dev"
Requires-Dist: flake8>=3.9; extra == "dev"
Dynamic: author
Dynamic: home-page
Dynamic: license-file
Dynamic: requires-python
